odoo/addons/auth_oauth_filter_by_domain/README.rst
odoo/addons/auth_oauth_filter_by_domain/__init__.py
odoo/addons/auth_oauth_filter_by_domain/__manifest__.py
odoo/addons/auth_oauth_filter_by_domain/controllers/__init__.py
odoo/addons/auth_oauth_filter_by_domain/controllers/main.py
odoo/addons/auth_oauth_filter_by_domain/i18n/auth_oauth_filter_by_domain.pot
odoo/addons/auth_oauth_filter_by_domain/i18n/it.po
odoo/addons/auth_oauth_filter_by_domain/models/__init__.py
odoo/addons/auth_oauth_filter_by_domain/models/auth_oauth.py
odoo/addons/auth_oauth_filter_by_domain/readme/CONTRIBUTORS.md
odoo/addons/auth_oauth_filter_by_domain/readme/DESCRIPTION.md
odoo/addons/auth_oauth_filter_by_domain/readme/USAGE.md
odoo/addons/auth_oauth_filter_by_domain/static/description/icon.png
odoo/addons/auth_oauth_filter_by_domain/static/description/index.html
odoo/addons/auth_oauth_filter_by_domain/views/auth_oauth_views.xml
odoo_addon_auth_oauth_filter_by_domain-18.0.1.0.0.4.dist-info/METADATA
odoo_addon_auth_oauth_filter_by_domain-18.0.1.0.0.4.dist-info/WHEEL
odoo_addon_auth_oauth_filter_by_domain-18.0.1.0.0.4.dist-info/top_level.txt
odoo_addon_auth_oauth_filter_by_domain-18.0.1.0.0.4.dist-info/RECORD
