Metadata-Version: 2.1
Name: odoo-addon-auth_oauth_filter_by_domain
Version: 18.0.1.0.0.4
Requires-Python: >=3.10
Requires-Dist: odoo==18.0.*
Summary: Filter OAuth providers by domain
Home-page: https://github.com/OCA/server-auth
License: AGPL-3
Author: Kencove, Odoo Community Association (OCA)
Author-email: support@odoo-community.org
Classifier: Programming Language :: Python
Classifier: Framework :: Odoo
Classifier: Framework :: Odoo :: 18.0
Classifier: License :: OSI Approved :: GNU Affero General Public License v3
